{
  "openapi": "3.0.0",
  "info": {
    "title": "Curio API",
    "version": "1.0.0",
    "description": "API documentation for Curio"
  },
  "servers": [
    {
      "url": "http://localhost:3000"
    }
  ],
  "components": {
    "schemas": {
      "Error": {
        "type": "object",
        "properties": {
          "error": {
            "type": "string",
            "description": "Error message"
          }
        },
        "required": [
          "error"
        ]
      }
    },
    "parameters": {}
  },
  "paths": {
    "/api/v1/user/username": {
      "post": {
        "description": "POST /api/v1/user/username",
        "tags": [
          "V1"
        ],
        "requestBody": {
          "description": "Request body",
          "required": true,
          "content": {
            "application/json": {
              "schema": {
                "type": "object",
                "properties": {
                  "username": {
                    "type": "string"
                  }
                },
                "required": [
                  "username"
                ]
              }
            }
          }
        },
        "responses": {
          "200": {
            "description": "Successful response",
            "content": {
              "application/json": {
                "schema": {
                  "type": "object",
                  "properties": {
                    "updatedUsername": {
                      "type": "string"
                    }
                  }
                }
              }
            }
          },
          "400": {
            "description": "Bad request",
            "content": {
              "application/json": {
                "schema": {
                  "type": "object",
                  "properties": {
                    "error": {
                      "type": "string",
                      "description": "Error message"
                    }
                  },
                  "required": [
                    "error"
                  ]
                }
              }
            }
          },
          "500": {
            "description": "Internal server error",
            "content": {
              "application/json": {
                "schema": {
                  "type": "object",
                  "properties": {
                    "error": {
                      "type": "string",
                      "description": "Error message"
                    }
                  },
                  "required": [
                    "error"
                  ]
                }
              }
            }
          }
        }
      }
    },
    "/api/v1/user/settings": {
      "get": {
        "description": "GET /api/v1/user/settings",
        "tags": [
          "V1"
        ],
        "responses": {
          "200": {
            "description": "Successful response",
            "content": {
              "application/json": {
                "schema": {
                  "type": "object",
                  "properties": {
                    "colorScheme": {
                      "type": "string",
                      "enum": [
                        "auto",
                        "light",
                        "dark"
                      ],
                      "description": "Color scheme to display."
                    }
                  },
                  "required": [
                    "colorScheme"
                  ],
                  "additionalProperties": false
                }
              }
            }
          },
          "400": {
            "description": "Bad request",
            "content": {
              "application/json": {
                "schema": {
                  "type": "object",
                  "properties": {
                    "error": {
                      "type": "string",
                      "description": "Error message"
                    }
                  },
                  "required": [
                    "error"
                  ]
                }
              }
            }
          },
          "500": {
            "description": "Internal server error",
            "content": {
              "application/json": {
                "schema": {
                  "type": "object",
                  "properties": {
                    "error": {
                      "type": "string",
                      "description": "Error message"
                    }
                  },
                  "required": [
                    "error"
                  ]
                }
              }
            }
          }
        }
      },
      "post": {
        "description": "POST /api/v1/user/settings",
        "tags": [
          "V1"
        ],
        "requestBody": {
          "description": "Request body",
          "required": true,
          "content": {
            "application/json": {
              "schema": {
                "type": "object",
                "properties": {
                  "colorScheme": {
                    "type": "string",
                    "enum": [
                      "auto",
                      "light",
                      "dark"
                    ],
                    "description": "Color scheme to display."
                  }
                },
                "additionalProperties": false
              }
            }
          }
        },
        "responses": {
          "200": {
            "description": "Successful response",
            "content": {
              "application/json": {
                "schema": {
                  "type": "object",
                  "properties": {
                    "colorScheme": {
                      "type": "string",
                      "enum": [
                        "auto",
                        "light",
                        "dark"
                      ],
                      "description": "Color scheme to display."
                    }
                  },
                  "required": [
                    "colorScheme"
                  ],
                  "additionalProperties": false
                }
              }
            }
          },
          "400": {
            "description": "Bad request",
            "content": {
              "application/json": {
                "schema": {
                  "type": "object",
                  "properties": {
                    "error": {
                      "type": "string",
                      "description": "Error message"
                    }
                  },
                  "required": [
                    "error"
                  ]
                }
              }
            }
          },
          "500": {
            "description": "Internal server error",
            "content": {
              "application/json": {
                "schema": {
                  "type": "object",
                  "properties": {
                    "error": {
                      "type": "string",
                      "description": "Error message"
                    }
                  },
                  "required": [
                    "error"
                  ]
                }
              }
            }
          }
        }
      }
    },
    "/api/v1/user/labels": {
      "get": {
        "description": "GET /api/v1/user/labels",
        "tags": [
          "V1"
        ],
        "responses": {
          "200": {
            "description": "Successful response",
            "content": {
              "application/json": {
                "schema": {
                  "type": "object",
                  "properties": {
                    "labels": {
                      "type": "array",
                      "items": {
                        "type": "object",
                        "properties": {
                          "id": {
                            "type": "string"
                          },
                          "name": {
                            "type": "string",
                            "minLength": 1,
                            "maxLength": 255
                          },
                          "color": {
                            "type": "string"
                          }
                        },
                        "required": [
                          "id",
                          "name",
                          "color"
                        ]
                      }
                    }
                  },
                  "required": [
                    "labels"
                  ]
                }
              }
            }
          },
          "400": {
            "description": "Bad request",
            "content": {
              "application/json": {
                "schema": {
                  "type": "object",
                  "properties": {
                    "error": {
                      "type": "string",
                      "description": "Error message"
                    }
                  },
                  "required": [
                    "error"
                  ]
                }
              }
            }
          },
          "500": {
            "description": "Internal server error",
            "content": {
              "application/json": {
                "schema": {
                  "type": "object",
                  "properties": {
                    "error": {
                      "type": "string",
                      "description": "Error message"
                    }
                  },
                  "required": [
                    "error"
                  ]
                }
              }
            }
          }
        }
      },
      "post": {
        "description": "POST /api/v1/user/labels",
        "tags": [
          "V1"
        ],
        "requestBody": {
          "description": "Request body",
          "required": true,
          "content": {
            "application/json": {
              "schema": {
                "type": "object",
                "properties": {
                  "labels": {
                    "type": "array",
                    "items": {
                      "anyOf": [
                        {
                          "type": "object",
                          "properties": {
                            "id": {
                              "type": "string"
                            },
                            "name": {
                              "type": "string",
                              "nullable": true,
                              "minLength": 1,
                              "maxLength": 255
                            },
                            "color": {
                              "type": "string",
                              "nullable": true
                            }
                          },
                          "required": [
                            "id"
                          ]
                        },
                        {
                          "type": "object",
                          "properties": {
                            "name": {
                              "type": "string",
                              "minLength": 1,
                              "maxLength": 255
                            },
                            "color": {
                              "type": "string"
                            }
                          },
                          "required": [
                            "name",
                            "color"
                          ]
                        }
                      ]
                    }
                  }
                },
                "required": [
                  "labels"
                ]
              }
            }
          }
        },
        "responses": {
          "200": {
            "description": "Successful response",
            "content": {
              "application/json": {
                "schema": {
                  "type": "object",
                  "properties": {
                    "labels": {
                      "type": "array",
                      "items": {
                        "type": "object",
                        "properties": {
                          "id": {
                            "type": "string"
                          },
                          "name": {
                            "type": "string",
                            "minLength": 1,
                            "maxLength": 255
                          },
                          "color": {
                            "type": "string"
                          }
                        },
                        "required": [
                          "id",
                          "name",
                          "color"
                        ]
                      }
                    }
                  },
                  "required": [
                    "labels"
                  ]
                }
              }
            }
          },
          "400": {
            "description": "Bad request",
            "content": {
              "application/json": {
                "schema": {
                  "type": "object",
                  "properties": {
                    "error": {
                      "type": "string",
                      "description": "Error message"
                    }
                  },
                  "required": [
                    "error"
                  ]
                }
              }
            }
          },
          "500": {
            "description": "Internal server error",
            "content": {
              "application/json": {
                "schema": {
                  "type": "object",
                  "properties": {
                    "error": {
                      "type": "string",
                      "description": "Error message"
                    }
                  },
                  "required": [
                    "error"
                  ]
                }
              }
            }
          }
        }
      },
      "delete": {
        "description": "DELETE /api/v1/user/labels",
        "tags": [
          "V1"
        ],
        "requestBody": {
          "description": "Request body",
          "required": true,
          "content": {
            "application/json": {
              "schema": {
                "type": "object",
                "properties": {
                  "ids": {
                    "type": "array",
                    "items": {
                      "type": "string"
                    }
                  }
                },
                "required": [
                  "ids"
                ]
              }
            }
          }
        },
        "responses": {
          "200": {
            "description": "Successful response",
            "content": {
              "application/json": {
                "schema": {
                  "type": "object",
                  "properties": {
                    "deleted": {
                      "type": "number"
                    }
                  },
                  "required": [
                    "deleted"
                  ]
                }
              }
            }
          },
          "400": {
            "description": "Bad request",
            "content": {
              "application/json": {
                "schema": {
                  "type": "object",
                  "properties": {
                    "error": {
                      "type": "string",
                      "description": "Error message"
                    }
                  },
                  "required": [
                    "error"
                  ]
                }
              }
            }
          },
          "500": {
            "description": "Internal server error",
            "content": {
              "application/json": {
                "schema": {
                  "type": "object",
                  "properties": {
                    "error": {
                      "type": "string",
                      "description": "Error message"
                    }
                  },
                  "required": [
                    "error"
                  ]
                }
              }
            }
          }
        }
      }
    },
    "/api/v1/items": {
      "get": {
        "description": "GET /api/v1/items",
        "tags": [
          "V1"
        ],
        "parameters": [
          {
            "schema": {
              "type": "object",
              "properties": {
                "slugs": {
                  "type": "string",
                  "description": "A comma-separated list of slugs to retrieve. If the slug is not found, it will be ignored."
                },
                "urls": {
                  "type": "string",
                  "description": "A comma-separated list of URLs to retrieve. If the URL is not found, it will be ignored."
                },
                "limit": {
                  "type": "number",
                  "minimum": 1,
                  "maximum": 1000,
                  "default": 100
                },
                "cursor": {
                  "type": "string",
                  "description": "The savedAt timestamp to start from."
                },
                "filters": {
                  "type": "string",
                  "description": "The filters to apply."
                },
                "search": {
                  "type": "string",
                  "maxLength": 100,
                  "description": "The search query to apply."
                }
              }
            },
            "required": true,
            "name": "value",
            "in": "query"
          }
        ],
        "responses": {
          "200": {
            "description": "Successful response",
            "content": {
              "application/json": {
                "schema": {
                  "type": "object",
                  "properties": {
                    "items": {
                      "type": "array",
                      "items": {
                        "type": "object",
                        "properties": {
                          "id": {
                            "type": "string"
                          },
                          "url": {
                            "type": "string",
                            "format": "uri",
                            "description": "Unique URL of the item."
                          },
                          "slug": {
                            "type": "string",
                            "description": "Unique slug for the item used to identify it in its URL."
                          },
                          "metadata": {
                            "type": "object",
                            "properties": {
                              "title": {
                                "type": "string",
                                "maxLength": 255,
                                "description": "The title of the item."
                              },
                              "description": {
                                "type": "string",
                                "nullable": true,
                                "maxLength": 2048,
                                "description": "The description of the item."
                              },
                              "author": {
                                "type": "string",
                                "nullable": true,
                                "maxLength": 255,
                                "description": "The author of the item."
                              },
                              "publishedAt": {
                                "anyOf": [
                                  {
                                    "type": "string"
                                  },
                                  {
                                    "type": "string"
                                  },
                                  {
                                    "nullable": true
                                  }
                                ],
                                "description": "The published date of the item."
                              },
                              "savedAt": {
                                "anyOf": [
                                  {
                                    "type": "string"
                                  },
                                  {
                                    "type": "string"
                                  },
                                  {
                                    "nullable": true
                                  }
                                ],
                                "description": "The time the item was saved. Populated automatically and cannot be user-overridden."
                              },
                              "stateUpdatedAt": {
                                "anyOf": [
                                  {
                                    "type": "string"
                                  },
                                  {
                                    "type": "string"
                                  },
                                  {
                                    "nullable": true
                                  }
                                ],
                                "description": "The time the item's state was last updated. Used to sort items in the feed."
                              },
                              "state": {
                                "type": "string",
                                "enum": [
                                  "active",
                                  "archived",
                                  "deleted"
                                ],
                                "description": "Whether the state is active or archived."
                              },
                              "isFavorite": {
                                "type": "boolean",
                                "description": "Whether the item is favorited."
                              },
                              "readingProgress": {
                                "type": "number",
                                "minimum": 0,
                                "maximum": 100,
                                "description": "Progress reading the item. Should only populated if versionName is set."
                              },
                              "lastReadAt": {
                                "anyOf": [
                                  {
                                    "type": "string"
                                  },
                                  {
                                    "type": "string"
                                  },
                                  {
                                    "nullable": true
                                  }
                                ],
                                "description": "The last read date of the item. Should only be populated if versionName is set."
                              },
                              "versionName": {
                                "type": "string",
                                "nullable": true,
                                "maxLength": 255,
                                "description": "The version name of the item."
                              },
                              "thumbnail": {
                                "type": "string",
                                "nullable": true,
                                "maxLength": 2048,
                                "description": "The thumbnail URL of the item."
                              },
                              "favicon": {
                                "type": "string",
                                "nullable": true,
                                "maxLength": 2048,
                                "description": "The favicon URL of the item."
                              }
                            },
                            "required": [
                              "title",
                              "state",
                              "isFavorite",
                              "readingProgress",
                              "versionName"
                            ],
                            "additionalProperties": false
                          },
                          "createdAt": {
                            "anyOf": [
                              {
                                "type": "string"
                              },
                              {
                                "type": "string"
                              }
                            ]
                          },
                          "labels": {
                            "type": "array",
                            "items": {
                              "type": "object",
                              "properties": {
                                "id": {
                                  "type": "string"
                                },
                                "name": {
                                  "type": "string",
                                  "minLength": 1,
                                  "maxLength": 255
                                },
                                "color": {
                                  "type": "string"
                                }
                              },
                              "required": [
                                "id",
                                "name",
                                "color"
                              ]
                            }
                          }
                        },
                        "required": [
                          "id",
                          "url",
                          "slug",
                          "metadata",
                          "createdAt",
                          "labels"
                        ],
                        "additionalProperties": false
                      }
                    },
                    "nextCursor": {
                      "type": "string"
                    },
                    "total": {
                      "type": "number"
                    }
                  },
                  "required": [
                    "items",
                    "total"
                  ]
                }
              }
            }
          },
          "400": {
            "description": "Bad request",
            "content": {
              "application/json": {
                "schema": {
                  "type": "object",
                  "properties": {
                    "error": {
                      "type": "string",
                      "description": "Error message"
                    }
                  },
                  "required": [
                    "error"
                  ]
                }
              }
            }
          },
          "500": {
            "description": "Internal server error",
            "content": {
              "application/json": {
                "schema": {
                  "type": "object",
                  "properties": {
                    "error": {
                      "type": "string",
                      "description": "Error message"
                    }
                  },
                  "required": [
                    "error"
                  ]
                }
              }
            }
          }
        }
      },
      "post": {
        "description": "POST /api/v1/items",
        "tags": [
          "V1"
        ],
        "requestBody": {
          "description": "Request body",
          "required": true,
          "content": {
            "application/json": {
              "schema": {
                "type": "object",
                "properties": {
                  "items": {
                    "type": "array",
                    "items": {
                      "type": "object",
                      "properties": {
                        "url": {
                          "type": "string",
                          "format": "uri",
                          "description": "Unique URL of the item."
                        },
                        "metadata": {
                          "type": "object",
                          "properties": {
                            "title": {
                              "type": "string",
                              "maxLength": 255,
                              "description": "The title of the item."
                            },
                            "description": {
                              "type": "string",
                              "nullable": true,
                              "maxLength": 2048,
                              "description": "The description of the item."
                            },
                            "author": {
                              "type": "string",
                              "nullable": true,
                              "maxLength": 255,
                              "description": "The author of the item."
                            },
                            "publishedAt": {
                              "anyOf": [
                                {
                                  "type": "string"
                                },
                                {
                                  "type": "string"
                                },
                                {
                                  "nullable": true
                                }
                              ],
                              "description": "The published date of the item."
                            },
                            "savedAt": {
                              "anyOf": [
                                {
                                  "type": "string"
                                },
                                {
                                  "type": "string"
                                },
                                {
                                  "nullable": true
                                }
                              ],
                              "description": "The time the item was saved. Populated automatically and cannot be user-overridden."
                            },
                            "stateUpdatedAt": {
                              "anyOf": [
                                {
                                  "type": "string"
                                },
                                {
                                  "type": "string"
                                },
                                {
                                  "nullable": true
                                }
                              ],
                              "description": "The time the item's state was last updated. Used to sort items in the feed."
                            },
                            "state": {
                              "type": "string",
                              "enum": [
                                "active",
                                "archived",
                                "deleted"
                              ],
                              "description": "Whether the state is active or archived."
                            },
                            "isFavorite": {
                              "type": "boolean",
                              "description": "Whether the item is favorited."
                            },
                            "readingProgress": {
                              "type": "number",
                              "minimum": 0,
                              "maximum": 100,
                              "description": "Progress reading the item. Should only populated if versionName is set."
                            },
                            "lastReadAt": {
                              "anyOf": [
                                {
                                  "type": "string"
                                },
                                {
                                  "type": "string"
                                },
                                {
                                  "nullable": true
                                }
                              ],
                              "description": "The last read date of the item. Should only be populated if versionName is set."
                            },
                            "versionName": {
                              "type": "string",
                              "nullable": true,
                              "maxLength": 255,
                              "description": "The version name of the item."
                            },
                            "thumbnail": {
                              "type": "string",
                              "nullable": true,
                              "maxLength": 2048,
                              "format": "uri",
                              "description": "The thumbnail URL of the item."
                            },
                            "favicon": {
                              "type": "string",
                              "nullable": true,
                              "maxLength": 2048,
                              "format": "uri",
                              "description": "The favicon URL of the item."
                            }
                          },
                          "additionalProperties": false
                        }
                      },
                      "required": [
                        "url"
                      ],
                      "additionalProperties": false
                    }
                  }
                },
                "required": [
                  "items"
                ]
              }
            }
          }
        },
        "responses": {
          "200": {
            "description": "Successful response",
            "content": {
              "application/json": {
                "schema": {
                  "type": "object",
                  "properties": {
                    "items": {
                      "type": "array",
                      "items": {
                        "type": "object",
                        "properties": {
                          "id": {
                            "type": "string"
                          },
                          "url": {
                            "type": "string",
                            "format": "uri",
                            "description": "Unique URL of the item."
                          },
                          "slug": {
                            "type": "string",
                            "description": "Unique slug for the item used to identify it in its URL."
                          },
                          "metadata": {
                            "type": "object",
                            "properties": {
                              "title": {
                                "type": "string",
                                "maxLength": 255,
                                "description": "The title of the item."
                              },
                              "description": {
                                "type": "string",
                                "nullable": true,
                                "maxLength": 2048,
                                "description": "The description of the item."
                              },
                              "author": {
                                "type": "string",
                                "nullable": true,
                                "maxLength": 255,
                                "description": "The author of the item."
                              },
                              "publishedAt": {
                                "anyOf": [
                                  {
                                    "type": "string"
                                  },
                                  {
                                    "type": "string"
                                  },
                                  {
                                    "nullable": true
                                  }
                                ],
                                "description": "The published date of the item."
                              },
                              "savedAt": {
                                "anyOf": [
                                  {
                                    "type": "string"
                                  },
                                  {
                                    "type": "string"
                                  },
                                  {
                                    "nullable": true
                                  }
                                ],
                                "description": "The time the item was saved. Populated automatically and cannot be user-overridden."
                              },
                              "stateUpdatedAt": {
                                "anyOf": [
                                  {
                                    "type": "string"
                                  },
                                  {
                                    "type": "string"
                                  },
                                  {
                                    "nullable": true
                                  }
                                ],
                                "description": "The time the item's state was last updated. Used to sort items in the feed."
                              },
                              "state": {
                                "type": "string",
                                "enum": [
                                  "active",
                                  "archived",
                                  "deleted"
                                ],
                                "description": "Whether the state is active or archived."
                              },
                              "isFavorite": {
                                "type": "boolean",
                                "description": "Whether the item is favorited."
                              },
                              "readingProgress": {
                                "type": "number",
                                "minimum": 0,
                                "maximum": 100,
                                "description": "Progress reading the item. Should only populated if versionName is set."
                              },
                              "lastReadAt": {
                                "anyOf": [
                                  {
                                    "type": "string"
                                  },
                                  {
                                    "type": "string"
                                  },
                                  {
                                    "nullable": true
                                  }
                                ],
                                "description": "The last read date of the item. Should only be populated if versionName is set."
                              },
                              "versionName": {
                                "type": "string",
                                "nullable": true,
                                "maxLength": 255,
                                "description": "The version name of the item."
                              },
                              "thumbnail": {
                                "type": "string",
                                "nullable": true,
                                "maxLength": 2048,
                                "description": "The thumbnail URL of the item."
                              },
                              "favicon": {
                                "type": "string",
                                "nullable": true,
                                "maxLength": 2048,
                                "description": "The favicon URL of the item."
                              }
                            },
                            "required": [
                              "title",
                              "state",
                              "isFavorite",
                              "readingProgress",
                              "versionName"
                            ],
                            "additionalProperties": false
                          },
                          "createdAt": {
                            "anyOf": [
                              {
                                "type": "string"
                              },
                              {
                                "type": "string"
                              }
                            ]
                          }
                        },
                        "required": [
                          "id",
                          "url",
                          "slug",
                          "metadata",
                          "createdAt"
                        ],
                        "additionalProperties": false
                      }
                    },
                    "errors": {
                      "type": "array",
                      "items": {
                        "type": "object",
                        "properties": {
                          "url": {
                            "type": "string"
                          },
                          "error": {
                            "type": "string"
                          }
                        },
                        "required": [
                          "url",
                          "error"
                        ]
                      }
                    }
                  },
                  "required": [
                    "items"
                  ]
                }
              }
            }
          },
          "400": {
            "description": "Bad request",
            "content": {
              "application/json": {
                "schema": {
                  "type": "object",
                  "properties": {
                    "error": {
                      "type": "string",
                      "description": "Error message"
                    }
                  },
                  "required": [
                    "error"
                  ]
                }
              }
            }
          },
          "500": {
            "description": "Internal server error",
            "content": {
              "application/json": {
                "schema": {
                  "type": "object",
                  "properties": {
                    "error": {
                      "type": "string",
                      "description": "Error message"
                    }
                  },
                  "required": [
                    "error"
                  ]
                }
              }
            }
          }
        }
      }
    },
    "/api/v1/items/state": {
      "post": {
        "description": "POST /api/v1/items/state",
        "tags": [
          "V1"
        ],
        "requestBody": {
          "description": "Request body",
          "required": true,
          "content": {
            "application/json": {
              "schema": {
                "type": "object",
                "properties": {
                  "slugs": {
                    "type": "string",
                    "description": "A comma-separated list of slugs to update. If the slug is not found, it will be ignored."
                  },
                  "state": {
                    "type": "string",
                    "description": "The new state of the items. Can be one of: active, archived, deleted "
                  }
                },
                "required": [
                  "slugs",
                  "state"
                ]
              }
            }
          }
        },
        "responses": {
          "200": {
            "description": "Successful response",
            "content": {
              "application/json": {
                "schema": {
                  "type": "object",
                  "properties": {
                    "updated": {
                      "type": "array",
                      "items": {
                        "type": "object",
                        "properties": {
                          "slug": {
                            "type": "string"
                          }
                        },
                        "required": [
                          "slug"
                        ]
                      },
                      "description": "A list of slugs that were successfully updated."
                    }
                  },
                  "required": [
                    "updated"
                  ]
                }
              }
            }
          },
          "400": {
            "description": "Bad request",
            "content": {
              "application/json": {
                "schema": {
                  "type": "object",
                  "properties": {
                    "error": {
                      "type": "string",
                      "description": "Error message"
                    }
                  },
                  "required": [
                    "error"
                  ]
                }
              }
            }
          },
          "500": {
            "description": "Internal server error",
            "content": {
              "application/json": {
                "schema": {
                  "type": "object",
                  "properties": {
                    "error": {
                      "type": "string",
                      "description": "Error message"
                    }
                  },
                  "required": [
                    "error"
                  ]
                }
              }
            }
          }
        }
      }
    },
    "/api/v1/items/read": {
      "post": {
        "description": "POST /api/v1/items/read",
        "tags": [
          "V1"
        ],
        "requestBody": {
          "description": "Request body",
          "required": true,
          "content": {
            "application/json": {
              "schema": {
                "type": "object",
                "properties": {
                  "slug": {
                    "type": "string"
                  },
                  "readingProgress": {
                    "type": "number",
                    "minimum": 0,
                    "maximum": 100
                  }
                },
                "required": [
                  "slug",
                  "readingProgress"
                ]
              }
            }
          }
        },
        "responses": {
          "200": {
            "description": "Successful response",
            "content": {
              "application/json": {
                "schema": {
                  "type": "object",
                  "properties": {
                    "slug": {
                      "type": "string"
                    },
                    "readingProgress": {
                      "type": "number",
                      "minimum": 0,
                      "maximum": 100
                    },
                    "versionName": {
                      "type": "string",
                      "nullable": true
                    }
                  },
                  "required": [
                    "slug",
                    "readingProgress",
                    "versionName"
                  ]
                }
              }
            }
          },
          "400": {
            "description": "Bad request",
            "content": {
              "application/json": {
                "schema": {
                  "type": "object",
                  "properties": {
                    "error": {
                      "type": "string",
                      "description": "Error message"
                    }
                  },
                  "required": [
                    "error"
                  ]
                }
              }
            }
          },
          "500": {
            "description": "Internal server error",
            "content": {
              "application/json": {
                "schema": {
                  "type": "object",
                  "properties": {
                    "error": {
                      "type": "string",
                      "description": "Error message"
                    }
                  },
                  "required": [
                    "error"
                  ]
                }
              }
            }
          }
        }
      }
    },
    "/api/v1/items/labels": {
      "post": {
        "description": "POST /api/v1/items/labels",
        "tags": [
          "V1"
        ],
        "requestBody": {
          "description": "Request body",
          "required": true,
          "content": {
            "application/json": {
              "schema": {
                "type": "object",
                "properties": {
                  "slugs": {
                    "type": "string",
                    "description": "A comma-separated list of slugs to update. If the slug is not found, it will be ignored."
                  },
                  "labelIds": {
                    "type": "array",
                    "items": {
                      "type": "string",
                      "format": "uuid"
                    },
                    "description": "An array of label UUIDs to apply to the specified items."
                  }
                },
                "required": [
                  "slugs",
                  "labelIds"
                ]
              }
            }
          }
        },
        "responses": {
          "200": {
            "description": "Successful response",
            "content": {
              "application/json": {
                "schema": {
                  "type": "object",
                  "properties": {
                    "updated": {
                      "type": "array",
                      "items": {
                        "type": "object",
                        "properties": {
                          "slug": {
                            "type": "string"
                          }
                        },
                        "required": [
                          "slug"
                        ]
                      },
                      "description": "A list of slugs that were successfully updated."
                    }
                  },
                  "required": [
                    "updated"
                  ]
                }
              }
            }
          },
          "400": {
            "description": "Bad request",
            "content": {
              "application/json": {
                "schema": {
                  "type": "object",
                  "properties": {
                    "error": {
                      "type": "string",
                      "description": "Error message"
                    }
                  },
                  "required": [
                    "error"
                  ]
                }
              }
            }
          },
          "500": {
            "description": "Internal server error",
            "content": {
              "application/json": {
                "schema": {
                  "type": "object",
                  "properties": {
                    "error": {
                      "type": "string",
                      "description": "Error message"
                    }
                  },
                  "required": [
                    "error"
                  ]
                }
              }
            }
          }
        }
      },
      "delete": {
        "description": "DELETE /api/v1/items/labels",
        "tags": [
          "V1"
        ],
        "requestBody": {
          "description": "Request body",
          "required": true,
          "content": {
            "application/json": {
              "schema": {
                "type": "object",
                "properties": {
                  "slugs": {
                    "type": "string",
                    "description": "A comma-separated list of slugs to remove labels from. If the slug is not found, it will be ignored."
                  },
                  "labelIds": {
                    "type": "array",
                    "items": {
                      "type": "string",
                      "format": "uuid"
                    },
                    "description": "An array of label UUIDs to remove from the specified items."
                  }
                },
                "required": [
                  "slugs",
                  "labelIds"
                ]
              }
            }
          }
        },
        "responses": {
          "200": {
            "description": "Successful response",
            "content": {
              "application/json": {
                "schema": {
                  "type": "object",
                  "properties": {
                    "deleted": {
                      "type": "array",
                      "items": {
                        "type": "object",
                        "properties": {
                          "slug": {
                            "type": "string"
                          }
                        },
                        "required": [
                          "slug"
                        ]
                      },
                      "description": "A list of slugs that had labels successfully deleted."
                    }
                  },
                  "required": [
                    "deleted"
                  ]
                }
              }
            }
          },
          "400": {
            "description": "Bad request",
            "content": {
              "application/json": {
                "schema": {
                  "type": "object",
                  "properties": {
                    "error": {
                      "type": "string",
                      "description": "Error message"
                    }
                  },
                  "required": [
                    "error"
                  ]
                }
              }
            }
          },
          "500": {
            "description": "Internal server error",
            "content": {
              "application/json": {
                "schema": {
                  "type": "object",
                  "properties": {
                    "error": {
                      "type": "string",
                      "description": "Error message"
                    }
                  },
                  "required": [
                    "error"
                  ]
                }
              }
            }
          }
        }
      }
    },
    "/api/v1/items/highlights": {
      "post": {
        "description": "POST /api/v1/items/highlights",
        "tags": [
          "V1"
        ],
        "requestBody": {
          "description": "Request body",
          "required": true,
          "content": {
            "application/json": {
              "schema": {
                "type": "object",
                "properties": {
                  "slug": {
                    "type": "string",
                    "description": "The slug of the item to add highlights to."
                  },
                  "highlights": {
                    "type": "array",
                    "items": {
                      "type": "object",
                      "properties": {
                        "id": {
                          "type": "string",
                          "format": "uuid",
                          "description": "Optional ID for updating an existing highlight"
                        },
                        "startOffset": {
                          "type": "number",
                          "minimum": 0,
                          "description": "Index of start position within its node"
                        },
                        "endOffset": {
                          "type": "number",
                          "minimum": 0,
                          "description": "Index of end position within its node"
                        },
                        "text": {
                          "type": "string",
                          "nullable": true,
                          "description": "The text of the highlight"
                        },
                        "note": {
                          "type": "string",
                          "nullable": true,
                          "description": "User note about the highlight"
                        }
                      },
                      "required": [
                        "startOffset",
                        "endOffset",
                        "text",
                        "note"
                      ]
                    }
                  }
                },
                "required": [
                  "slug",
                  "highlights"
                ]
              }
            }
          }
        },
        "responses": {
          "200": {
            "description": "Successful response",
            "content": {
              "application/json": {
                "schema": {
                  "type": "object",
                  "properties": {
                    "highlights": {
                      "type": "array",
                      "items": {
                        "type": "object",
                        "properties": {
                          "id": {
                            "type": "string",
                            "format": "uuid"
                          },
                          "startOffset": {
                            "type": "number",
                            "minimum": 0,
                            "description": "Index of start position within its node"
                          },
                          "endOffset": {
                            "type": "number",
                            "minimum": 0,
                            "description": "Index of end position within its node"
                          },
                          "text": {
                            "type": "string",
                            "nullable": true,
                            "description": "The text of the highlight"
                          },
                          "note": {
                            "type": "string",
                            "nullable": true,
                            "description": "User note about the highlight"
                          }
                        },
                        "required": [
                          "id",
                          "startOffset",
                          "endOffset",
                          "text",
                          "note"
                        ]
                      }
                    }
                  },
                  "required": [
                    "highlights"
                  ]
                }
              }
            }
          },
          "400": {
            "description": "Bad request",
            "content": {
              "application/json": {
                "schema": {
                  "type": "object",
                  "properties": {
                    "error": {
                      "type": "string",
                      "description": "Error message"
                    }
                  },
                  "required": [
                    "error"
                  ]
                }
              }
            }
          },
          "500": {
            "description": "Internal server error",
            "content": {
              "application/json": {
                "schema": {
                  "type": "object",
                  "properties": {
                    "error": {
                      "type": "string",
                      "description": "Error message"
                    }
                  },
                  "required": [
                    "error"
                  ]
                }
              }
            }
          }
        }
      },
      "delete": {
        "description": "DELETE /api/v1/items/highlights",
        "tags": [
          "V1"
        ],
        "requestBody": {
          "description": "Request body",
          "required": true,
          "content": {
            "application/json": {
              "schema": {
                "type": "object",
                "properties": {
                  "slug": {
                    "type": "string",
                    "description": "The slug of the item to delete highlights from."
                  },
                  "highlightIds": {
                    "type": "array",
                    "items": {
                      "type": "string",
                      "format": "uuid"
                    },
                    "minItems": 1,
                    "description": "Array of highlight IDs to delete"
                  }
                },
                "required": [
                  "slug",
                  "highlightIds"
                ]
              }
            }
          }
        },
        "responses": {
          "200": {
            "description": "Successful response",
            "content": {
              "application/json": {
                "schema": {
                  "type": "object",
                  "properties": {
                    "deleted": {
                      "type": "array",
                      "items": {
                        "type": "object",
                        "properties": {
                          "id": {
                            "type": "string",
                            "format": "uuid"
                          }
                        },
                        "required": [
                          "id"
                        ]
                      }
                    }
                  },
                  "required": [
                    "deleted"
                  ]
                }
              }
            }
          },
          "400": {
            "description": "Bad request",
            "content": {
              "application/json": {
                "schema": {
                  "type": "object",
                  "properties": {
                    "error": {
                      "type": "string",
                      "description": "Error message"
                    }
                  },
                  "required": [
                    "error"
                  ]
                }
              }
            }
          },
          "500": {
            "description": "Internal server error",
            "content": {
              "application/json": {
                "schema": {
                  "type": "object",
                  "properties": {
                    "error": {
                      "type": "string",
                      "description": "Error message"
                    }
                  },
                  "required": [
                    "error"
                  ]
                }
              }
            }
          }
        }
      }
    },
    "/api/v1/items/favorite": {
      "post": {
        "description": "POST /api/v1/items/favorite",
        "tags": [
          "V1"
        ],
        "requestBody": {
          "description": "Request body",
          "required": true,
          "content": {
            "application/json": {
              "schema": {
                "type": "object",
                "properties": {
                  "slugs": {
                    "type": "string",
                    "description": "A comma-separated list of slugs to update. If the slug is not found, it will be ignored."
                  },
                  "favorite": {
                    "type": "boolean",
                    "description": "Whether the items should be favorited or unfavorited."
                  }
                },
                "required": [
                  "slugs",
                  "favorite"
                ]
              }
            }
          }
        },
        "responses": {
          "200": {
            "description": "Successful response",
            "content": {
              "application/json": {
                "schema": {
                  "type": "object",
                  "properties": {
                    "updated": {
                      "type": "array",
                      "items": {
                        "type": "object",
                        "properties": {
                          "slug": {
                            "type": "string"
                          }
                        },
                        "required": [
                          "slug"
                        ]
                      },
                      "description": "A list of slugs that were successfully updated."
                    }
                  },
                  "required": [
                    "updated"
                  ]
                }
              }
            }
          },
          "400": {
            "description": "Bad request",
            "content": {
              "application/json": {
                "schema": {
                  "type": "object",
                  "properties": {
                    "error": {
                      "type": "string",
                      "description": "Error message"
                    }
                  },
                  "required": [
                    "error"
                  ]
                }
              }
            }
          },
          "500": {
            "description": "Internal server error",
            "content": {
              "application/json": {
                "schema": {
                  "type": "object",
                  "properties": {
                    "error": {
                      "type": "string",
                      "description": "Error message"
                    }
                  },
                  "required": [
                    "error"
                  ]
                }
              }
            }
          }
        }
      }
    },
    "/api/v1/items/content": {
      "get": {
        "description": "GET /api/v1/items/content",
        "tags": [
          "V1"
        ],
        "parameters": [
          {
            "schema": {
              "type": "string",
              "description": "The unique slug of the item to retrieve."
            },
            "required": true,
            "description": "The unique slug of the item to retrieve.",
            "name": "slug",
            "in": "query"
          }
        ],
        "responses": {
          "200": {
            "description": "Successful response",
            "content": {
              "application/json": {
                "schema": {
                  "anyOf": [
                    {
                      "type": "object",
                      "properties": {
                        "content": {
                          "type": "string"
                        },
                        "item": {
                          "type": "object",
                          "properties": {
                            "id": {
                              "type": "string"
                            },
                            "url": {
                              "type": "string",
                              "format": "uri",
                              "description": "Unique URL of the item."
                            },
                            "slug": {
                              "type": "string",
                              "description": "Unique slug for the item used to identify it in its URL."
                            },
                            "metadata": {
                              "type": "object",
                              "properties": {
                                "title": {
                                  "type": "string",
                                  "maxLength": 255,
                                  "description": "The title of the item."
                                },
                                "description": {
                                  "type": "string",
                                  "nullable": true,
                                  "maxLength": 2048,
                                  "description": "The description of the item."
                                },
                                "author": {
                                  "type": "string",
                                  "nullable": true,
                                  "maxLength": 255,
                                  "description": "The author of the item."
                                },
                                "publishedAt": {
                                  "anyOf": [
                                    {
                                      "type": "string"
                                    },
                                    {
                                      "type": "string"
                                    },
                                    {
                                      "nullable": true
                                    }
                                  ],
                                  "description": "The published date of the item."
                                },
                                "savedAt": {
                                  "anyOf": [
                                    {
                                      "type": "string"
                                    },
                                    {
                                      "type": "string"
                                    },
                                    {
                                      "nullable": true
                                    }
                                  ],
                                  "description": "The time the item was saved. Populated automatically and cannot be user-overridden."
                                },
                                "stateUpdatedAt": {
                                  "anyOf": [
                                    {
                                      "type": "string"
                                    },
                                    {
                                      "type": "string"
                                    },
                                    {
                                      "nullable": true
                                    }
                                  ],
                                  "description": "The time the item's state was last updated. Used to sort items in the feed."
                                },
                                "state": {
                                  "type": "string",
                                  "enum": [
                                    "active",
                                    "archived",
                                    "deleted"
                                  ],
                                  "description": "Whether the state is active or archived."
                                },
                                "isFavorite": {
                                  "type": "boolean",
                                  "description": "Whether the item is favorited."
                                },
                                "readingProgress": {
                                  "type": "number",
                                  "minimum": 0,
                                  "maximum": 100,
                                  "description": "Progress reading the item. Should only populated if versionName is set."
                                },
                                "lastReadAt": {
                                  "anyOf": [
                                    {
                                      "type": "string"
                                    },
                                    {
                                      "type": "string"
                                    },
                                    {
                                      "nullable": true
                                    }
                                  ],
                                  "description": "The last read date of the item. Should only be populated if versionName is set."
                                },
                                "versionName": {
                                  "type": "string",
                                  "nullable": true,
                                  "maxLength": 255,
                                  "description": "The version name of the item."
                                },
                                "thumbnail": {
                                  "type": "string",
                                  "nullable": true,
                                  "maxLength": 2048,
                                  "description": "The thumbnail URL of the item."
                                },
                                "favicon": {
                                  "type": "string",
                                  "nullable": true,
                                  "maxLength": 2048,
                                  "description": "The favicon URL of the item."
                                }
                              },
                              "required": [
                                "title",
                                "state",
                                "isFavorite",
                                "readingProgress",
                                "versionName"
                              ],
                              "additionalProperties": false
                            },
                            "createdAt": {
                              "anyOf": [
                                {
                                  "type": "string"
                                },
                                {
                                  "type": "string"
                                }
                              ]
                            },
                            "labels": {
                              "type": "array",
                              "items": {
                                "type": "object",
                                "properties": {
                                  "id": {
                                    "type": "string"
                                  },
                                  "name": {
                                    "type": "string",
                                    "minLength": 1,
                                    "maxLength": 255
                                  },
                                  "color": {
                                    "type": "string"
                                  }
                                },
                                "required": [
                                  "id",
                                  "name",
                                  "color"
                                ]
                              }
                            },
                            "highlights": {
                              "type": "array",
                              "items": {
                                "type": "object",
                                "properties": {
                                  "id": {
                                    "type": "string"
                                  },
                                  "startOffset": {
                                    "type": "number"
                                  },
                                  "endOffset": {
                                    "type": "number"
                                  },
                                  "text": {
                                    "type": "string",
                                    "nullable": true
                                  },
                                  "note": {
                                    "type": "string",
                                    "nullable": true
                                  }
                                },
                                "required": [
                                  "id",
                                  "startOffset",
                                  "endOffset",
                                  "text",
                                  "note"
                                ]
                              }
                            }
                          },
                          "required": [
                            "id",
                            "url",
                            "slug",
                            "metadata",
                            "createdAt",
                            "labels",
                            "highlights"
                          ],
                          "additionalProperties": false
                        }
                      },
                      "required": [
                        "item"
                      ]
                    },
                    {
                      "type": "object",
                      "properties": {
                        "error": {
                          "type": "string"
                        }
                      },
                      "required": [
                        "error"
                      ]
                    }
                  ]
                }
              }
            }
          },
          "400": {
            "description": "Bad request",
            "content": {
              "application/json": {
                "schema": {
                  "type": "object",
                  "properties": {
                    "error": {
                      "type": "string",
                      "description": "Error message"
                    }
                  },
                  "required": [
                    "error"
                  ]
                }
              }
            }
          },
          "500": {
            "description": "Internal server error",
            "content": {
              "application/json": {
                "schema": {
                  "type": "object",
                  "properties": {
                    "error": {
                      "type": "string",
                      "description": "Error message"
                    }
                  },
                  "required": [
                    "error"
                  ]
                }
              }
            }
          }
        }
      },
      "post": {
        "description": "POST /api/v1/items/content",
        "tags": [
          "V1"
        ],
        "requestBody": {
          "description": "Request body",
          "required": true,
          "content": {
            "application/json": {
              "schema": {
                "type": "object",
                "properties": {
                  "htmlContent": {
                    "type": "string",
                    "description": "The HTML content for the item. Will replace the existing content only if it's longer."
                  },
                  "url": {
                    "type": "string",
                    "description": "The URL of the item to update."
                  },
                  "skipMetadataExtraction": {
                    "type": "boolean",
                    "default": false
                  }
                },
                "required": [
                  "htmlContent",
                  "url"
                ]
              }
            }
          }
        },
        "responses": {
          "200": {
            "description": "Successful response",
            "content": {
              "application/json": {
                "schema": {
                  "oneOf": [
                    {
                      "type": "object",
                      "properties": {
                        "status": {
                          "type": "string",
                          "enum": [
                            "UPDATED_MAIN"
                          ]
                        },
                        "slug": {
                          "type": "string"
                        },
                        "message": {
                          "type": "string"
                        }
                      },
                      "required": [
                        "status",
                        "slug",
                        "message"
                      ]
                    },
                    {
                      "type": "object",
                      "properties": {
                        "status": {
                          "type": "string",
                          "enum": [
                            "STORED_VERSION"
                          ]
                        },
                        "slug": {
                          "type": "string"
                        },
                        "message": {
                          "type": "string"
                        }
                      },
                      "required": [
                        "status",
                        "slug",
                        "message"
                      ]
                    },
                    {
                      "type": "object",
                      "properties": {
                        "status": {
                          "type": "string",
                          "enum": [
                            "SKIPPED"
                          ]
                        },
                        "slug": {
                          "type": "string"
                        },
                        "message": {
                          "type": "string"
                        }
                      },
                      "required": [
                        "status",
                        "slug",
                        "message"
                      ]
                    },
                    {
                      "type": "object",
                      "properties": {
                        "status": {
                          "type": "string",
                          "enum": [
                            "ERROR"
                          ]
                        },
                        "error": {
                          "type": "string"
                        }
                      },
                      "required": [
                        "status",
                        "error"
                      ]
                    }
                  ]
                }
              }
            }
          },
          "400": {
            "description": "Bad request",
            "content": {
              "application/json": {
                "schema": {
                  "type": "object",
                  "properties": {
                    "error": {
                      "type": "string",
                      "description": "Error message"
                    }
                  },
                  "required": [
                    "error"
                  ]
                }
              }
            }
          },
          "500": {
            "description": "Internal server error",
            "content": {
              "application/json": {
                "schema": {
                  "type": "object",
                  "properties": {
                    "error": {
                      "type": "string",
                      "description": "Error message"
                    }
                  },
                  "required": [
                    "error"
                  ]
                }
              }
            }
          }
        }
      }
    },
    "/api/v1/health": {
      "get": {
        "description": "GET /api/v1/health",
        "tags": [
          "V1"
        ],
        "responses": {
          "200": {
            "description": "Successful response",
            "content": {
              "application/json": {
                "schema": {
                  "type": "object",
                  "properties": {
                    "healthy": {
                      "type": "boolean",
                      "description": "Health status of the service"
                    }
                  },
                  "required": [
                    "healthy"
                  ]
                }
              }
            }
          },
          "400": {
            "description": "Bad request",
            "content": {
              "application/json": {
                "schema": {
                  "type": "object",
                  "properties": {
                    "error": {
                      "type": "string",
                      "description": "Error message"
                    }
                  },
                  "required": [
                    "error"
                  ]
                }
              }
            }
          },
          "500": {
            "description": "Internal server error",
            "content": {
              "application/json": {
                "schema": {
                  "type": "object",
                  "properties": {
                    "error": {
                      "type": "string",
                      "description": "Error message"
                    }
                  },
                  "required": [
                    "error"
                  ]
                }
              }
            }
          }
        }
      }
    }
  }
}